<?xml version="1.0" encoding="utf-8"?>
<UserInterfaceSettings>
  <LyricsFormat>
    <FontName>Lucida Console</FontName>
    <FontSize>12</FontSize>
    <FontStyle>Regular</FontStyle>
    <FontColorHex>#000000</FontColorHex>
  </LyricsFormat>
  <NoteFormat>
    <FontName>monospace</FontName>
    <FontSize>16</FontSize>
    <FontStyle>Regular</FontStyle>
    <FontColorHex>#000000</FontColorHex>
  </NoteFormat>
  <TextboxFormat>
    <FontName>serif</FontName>
    <FontSize>9</FontSize>
    <FontStyle>Regular</FontStyle>
    <FontColorHex>#000000</FontColorHex>
  </TextboxFormat>
  <LabelFormat>
    <FontName>serif</FontName>
    <FontSize>9</FontSize>
    <FontStyle>Regular</FontStyle>
    <FontColorHex>#000000</FontColorHex>
  </LabelFormat>
</UserInterfaceSettings>